README.rst
setup.cfg
setup.py
src/Vocabulary_Generator.egg-info/PKG-INFO
src/Vocabulary_Generator.egg-info/SOURCES.txt
src/Vocabulary_Generator.egg-info/dependency_links.txt
src/Vocabulary_Generator.egg-info/requires.txt
src/Vocabulary_Generator.egg-info/top_level.txt
src/vocabulary_generator/__init__.py
src/vocabulary_generator/core.py
src/vocabulary_generator.egg-info/PKG-INFO
src/vocabulary_generator.egg-info/SOURCES.txt
src/vocabulary_generator.egg-info/dependency_links.txt
src/vocabulary_generator.egg-info/requires.txt
src/vocabulary_generator.egg-info/top_level.txt