Metadata-Version: 2.1
Name: vocabulary-generator
Version: 0.0.1
Summary: Simple search unknown words in text.
Home-page: UNKNOWN
Author: Daria Zakharova
Author-email: zakharovadaria96@gmail.com
License: MIT
Project-URL: Code, https://github.com/zakharovadaria/vocabulary_generator
Project-URL: Issue tracker, https://github.com/zakharovadaria/vocabulary_generator/issues
Platform: UNKNOWN
Provides-Extra: dev
